metrics/__init__.py
metrics/metrics.py
metrics/syllables_en.py
metrics/test_metrics.py
metrics/utils.py
readability_metrics-1.0.0.dist-info/LICENSE
readability_metrics-1.0.0.dist-info/METADATA
readability_metrics-1.0.0.dist-info/WHEEL
readability_metrics-1.0.0.dist-info/top_level.txt
readability_metrics-1.0.0.dist-info/RECORD
