Metadata-Version: 2.1
Name: readability-metrics
Version: 1.0.0
Summary: Calculates multiple readability metrics for large documents.
Home-page: https://github.com/EricWiener/readability-metrics
Author: Eric Wiener
Author-email: ericwiener3@gmail.com
License: UNKNOWN
Platform: UNKNOWN
Classifier: Programming Language :: Python :: 3
Classifier: License :: OSI Approved :: MIT License
Classifier: Operating System :: OS Independent
Requires-Dist: nltk
